titiler/stacapi/__init__.py
titiler/stacapi/backend.py
titiler/stacapi/dependencies.py
titiler/stacapi/enums.py
titiler/stacapi/factory.py
titiler/stacapi/logger.py
titiler/stacapi/main.py
titiler/stacapi/models.py
titiler/stacapi/py.typed
titiler/stacapi/reader.py
titiler/stacapi/settings.py
titiler/stacapi/utils.py
titiler/stacapi/pystac/__init__.py
titiler/stacapi/pystac/advanced_client.py
titiler/stacapi/templates/debug.html
titiler/stacapi/templates/footer.html
titiler/stacapi/templates/header.html
titiler/stacapi/templates/landing.html
titiler/stacapi/templates/map.html
titiler/stacapi/templates/wmts-getcapabilities_1.0.0.xml
titiler_stacapi-0.4.0.dist-info/METADATA
titiler_stacapi-0.4.0.dist-info/WHEEL
titiler_stacapi-0.4.0.dist-info/licenses/LICENSE
titiler_stacapi-0.4.0.dist-info/RECORD
