Metadata-Version: 2.4
Name: titiler-stacapi
Version: 0.4.0
Summary: Connect titiler to STAC APIs.
Project-URL: Homepage, https://developmentseed.org/titiler-stacapi/
Project-URL: Documentation, https://developmentseed.org/titiler-stacapi/
Project-URL: Issues, https://github.com/developmentseed/titiler-stacapi/issues
Project-URL: Source, https://github.com/developmentseed/titiler-stacapi
Project-URL: Changelog, https://developmentseed.org/titiler-stacapi/release-notes/
Author-email: Vincent Sarago <vincent@developmentseed.com>
License: MIT License
License-File: LICENSE
Keywords: STAC API,TiTiler
Classifier: Intended Audience :: Information Technology
Classifier: Intended Audience :: Science/Research
Classifier: License :: OSI Approved :: MIT License
Classifier: Programming Language :: Python :: 3.11
Classifier: Programming Language :: Python :: 3.12
Classifier: Programming Language :: Python :: 3.13
Classifier: Topic :: Scientific/Engineering :: GIS
Requires-Python: <3.14,>=3.11
Requires-Dist: orjson
Requires-Dist: pydantic-settings~=2.0
Requires-Dist: pydantic<3.0,>=2.4
Requires-Dist: pystac-client
Requires-Dist: titiler-core<0.20,>=0.19.0
Requires-Dist: titiler-mosaic<0.20,>=0.19.0
Provides-Extra: server
Requires-Dist: uvicorn[standard]>=0.12.0; extra == 'server'
